SeqVectorizer/__init__.py
SeqVectorizer-0.5.dist-info/LICENSE
SeqVectorizer-0.5.dist-info/METADATA
SeqVectorizer-0.5.dist-info/WHEEL
SeqVectorizer-0.5.dist-info/top_level.txt
SeqVectorizer-0.5.dist-info/RECORD
