Metadata-Version: 2.1
Name: SeqVectorizer
Version: 0.5
Summary: UNKNOWN
Home-page: https://github.com/Kowsher/Impact-Learning-
Author: Kowsher Ahmed, Avishek Das
Author-email: ahmedshuvo969@gmail.com, avishek.das.ayan@gmail.com
License: MIT
Platform: UNKNOWN
Classifier: Programming Language :: Python :: 3
Classifier: License :: OSI Approved :: MIT License
Classifier: Operating System :: OS Independent
Requires-Dist: nltk
Requires-Dist: numpy (==1.18.5)
